pydantic_aws/__init__.py
pydantic_aws/cli.py
pydantic_aws/pydantic_aws.py
pydantic_aws/iam/__init__.py
pydantic_aws/iam/policy.py
pydantic_aws-0.1.0.dist-info/AUTHORS.rst
pydantic_aws-0.1.0.dist-info/LICENSE
pydantic_aws-0.1.0.dist-info/METADATA
pydantic_aws-0.1.0.dist-info/WHEEL
pydantic_aws-0.1.0.dist-info/top_level.txt
pydantic_aws-0.1.0.dist-info/RECORD
