Metadata-Version: 2.1
Name: pydantic_aws
Version: 0.1.0
Summary: Pydantic data validation for AWS models
Author-email: Aaron Lelevier <aaron.lelevier@gmail.com>
Maintainer-email: Aaron Lelevier <aaron.lelevier@gmail.com>
License: MIT license
Project-URL: bugs, https://github.com/aaronlelevier/pydantic_aws/issues
Project-URL: changelog, https://github.com/aaronlelevier/pydantic_aws/blob/master/changelog.md
Project-URL: homepage, https://github.com/aaronlelevier/pydantic_aws
License-File: LICENSE
License-File: AUTHORS.rst
Requires-Dist: pydantic
Provides-Extra: dev
Requires-Dist: coverage ; extra == 'dev'
Requires-Dist: mypy ; extra == 'dev'
Requires-Dist: pytest ; extra == 'dev'
Requires-Dist: ruff ; extra == 'dev'
